{
  "EN": [
    { "text": "ЁЯО╢ NaaM FM launches new radio show!", "link": "#" },
    { "text": "ЁЯФе Special interview with top RJ tonight!", "link": "#" },
    { "text": "ЁЯУ╗ Stream live from Chennai studio!", "link": "#" },
    { "text": "ЁЯМР Visit our website for more updates", "link": "#" }
  ],
  "TN": [
    { "text": "ЁЯО╢ роироорпН роОроГрокрпН.роОроорпН рокрпБродро┐роп ро░рпЗроЯро┐ропрпЛ роиро┐роХро┤рпНроЪрпНроЪро┐ родрпКроЯроЩрпНроХро┐ропродрпБ!", "link": "#" },
    { "text": "ЁЯФе роЪро┐ро▒рокрпНрокрпБ рокрпЗроЯрпНроЯро┐ роЗройрпНро▒рпБ роЗро░ро╡рпБ RJ роЙроЯройрпН!", "link": "#" },
    { "text": "ЁЯУ╗ роЪрпЖройрпНройрпИ ро╕рпНроЯрпБроЯро┐ропрпЛро╡ро┐ро▓рпН роЗро░рпБроирпНродрпБ роирпЗро░ро▓рпИ!", "link": "#" },
    { "text": "ЁЯМР роорпЗро▓рпБроорпН родроХро╡ро▓рпНроХро│рпБроХрпНроХрпБ роОроЩрпНроХро│рпН ро╡ро▓рпИродрпНродро│родрпНродрпИ рокро╛ро░рпНро╡рпИропро┐роЯрпБроЩрпНроХро│рпН", "link": "#" }
  ]
}
